ax3_mercadopago/__init__.py
ax3_mercadopago/admin.py
ax3_mercadopago/api.py
ax3_mercadopago/apps.py
ax3_mercadopago/cache_keys.py
ax3_mercadopago/data.py
ax3_mercadopago/exceptions.py
ax3_mercadopago/managers.py
ax3_mercadopago/models.py
ax3_mercadopago/settings.py
ax3_mercadopago/urls.py
ax3_mercadopago/utils.py
ax3_mercadopago/views.py
ax3_mercadopago/migrations/0001_initial.py
ax3_mercadopago/migrations/0002_auto_20200819_1812.py
ax3_mercadopago/migrations/__init__.py
AX3_Mercadopago-0.3.7.dist-info/LICENSE
AX3_Mercadopago-0.3.7.dist-info/METADATA
AX3_Mercadopago-0.3.7.dist-info/WHEEL
AX3_Mercadopago-0.3.7.dist-info/top_level.txt
AX3_Mercadopago-0.3.7.dist-info/RECORD
