Metadata-Version: 2.1
Name: AX3-Mercadopago
Version: 0.3.7
Summary: A Django app to add support for Mercadopago payments
Home-page: https://github.com/Axiacore/ax3-mercadopago
Author: Axiacore, 
Author-email: info@axiacore.com
License: UNKNOWN
Platform: UNKNOWN
Classifier: Environment :: Web Environment
Classifier: Framework :: Django
Classifier: Framework :: Django :: 2.2
Classifier: Intended Audience :: Developers
Classifier: License :: OSI Approved :: MIT License
Classifier: Operating System :: OS Independent
Classifier: Programming Language :: Python :: 3.6
Classifier: Topic :: Internet :: WWW/HTTP
Classifier: Topic :: Internet :: WWW/HTTP :: Dynamic Content
Requires-Dist: django (>=3.1.0)
Requires-Dist: pymercadopago (>=0.3.0)
Requires-Dist: python-dateutil (>=2.8.1)
